README.rst
fbpca.py
setup.py
fbpca.egg-info/PKG-INFO
fbpca.egg-info/SOURCES.txt
fbpca.egg-info/dependency_links.txt
fbpca.egg-info/top_level.txt