Metadata-Version: 1.1
Name: fbpca
Version: 1.0
Summary: Fast computations of PCA/SVD/eigendecompositions via randomized methods
Home-page: https://www.facebook.com
Author: tulloch@fb.com
Author-email: tulloch@fb.com
License: BSD License
Platform: Any
Classifier: Intended Audience :: Science/Research
Classifier: Intended Audience :: Developers
Classifier: License :: OSI Approved
Classifier: Programming Language :: C
Classifier: Programming Language :: Python
Classifier: Topic :: Software Development
Classifier: Topic :: Scientific/Engineering
Classifier: Operating System :: Microsoft :: Windows
Classifier: Operating System :: POSIX
Classifier: Operating System :: Unix
Classifier: Operating System :: MacOS
Classifier: Programming Language :: Python :: 2
Classifier: Programming Language :: Python :: 2.7
Classifier: Programming Language :: Python :: 3
Classifier: Programming Language :: Python :: 3.3
